MANIFEST.in
setup.py
raml_codec/__init__.py
raml_codec/decode.py
raml_codec/encode.py
raml_codec.egg-info/PKG-INFO
raml_codec.egg-info/SOURCES.txt
raml_codec.egg-info/dependency_links.txt
raml_codec.egg-info/entry_points.txt
raml_codec.egg-info/requires.txt
raml_codec.egg-info/top_level.txt