Metadata-Version: 1.1
Name: raml-codec
Version: 0.1.4
Summary: A RAML codec for Core API.
Home-page: http://github.com/core-api/python-raml-codec/
Author: Tom Christie
Author-email: tom@tomchristie.com
License: BSD
Platform: UNKNOWN
Classifier: Intended Audience :: Developers
Classifier: License :: OSI Approved :: BSD License
Classifier: Operating System :: OS Independent
Classifier: Programming Language :: Python
Classifier: Programming Language :: Python :: 3
